{"program_fname": "8_kmeans_16_cluster", "mutual_attribute": [{"n_cluster": 16, "n_instance": 8}], "dataset_partition": [{"type": "kmeans", "max_iter": 40, "program_train_para_dir": "/home/bz/NN_as_Classification/train_para/8_kmeans_16_cluster", "n_cluster": 16, "n_instance": 8, "kahip_dir": "/home/bz/KaHIP", "entity_number": 1}], "prepare_train_sample": [{"type": "neighbor", "output": "knn", "label_k": 50, "batch_size": 64, "shuffle": true, "train_split": 0.99, "save_dir": "/home/bz/NN_as_Classification/train_para/8_kmeans_16_cluster/Classifier_1_8", "n_cluster": 16, "entity_number": 1, "classifier_number": 8}], "train_model": [{"type": "neural_network", "network": {"n_input": 128, "n_hidden": [512, 512], "p_dropout": 0.1, "n_output": 16}, "n_epochs": 5, "lr": 0.008, "acc_threshold": 0.95, "save_dir": "/home/bz/NN_as_Classification/train_para/8_kmeans_16_cluster/Classifier_1_8", "n_cluster": 16, "entity_number": 1, "classifier_number": 8}], "result_integrate": {}, "n_total_classifier": 8, "n_config_entity": 1}